spminfo/__init__.py
spminfo/shahzi.py
spminfo-0.0.3.dist-info/LICENSE
spminfo-0.0.3.dist-info/METADATA
spminfo-0.0.3.dist-info/WHEEL
spminfo-0.0.3.dist-info/top_level.txt
spminfo-0.0.3.dist-info/RECORD
