Metadata-Version: 2.1
Name: spminfo
Version: 0.0.3
Summary: Team Musibat Bots
Home-page: https://bitbucket.org/shahzain83/musibat
Author: Shahzain Khan
Author-email: asifjamali83@hotmail.com
License: MIT
Project-URL: Bug Tracker, https://bitbucket.org/shahzain83/musibat/issues
Platform: UNKNOWN
License-File: LICENSE
Requires-Dist: requests
